pyreshaper/__init__.py
pyreshaper/iobackend.py
pyreshaper/reshaper.py
pyreshaper/specification.py
pyreshaper/cli/__init__.py
pyreshaper/cli/s2smake.py
pyreshaper/cli/s2srun.py
tests/__init__.py
tests/checks.py
tests/test_cli_parallel.py
tests/test_iobackend.py
tests/test_reshaper.py
tests/test_s2smake.py
tests/test_s2srun.py
tests/test_specification.py
tests/data/__init__.py
tests/data/config.py
tests/data/make.py
PyReshaper-1.1.1.dist-info/LICENSE.txt
PyReshaper-1.1.1.dist-info/METADATA
PyReshaper-1.1.1.dist-info/WHEEL
PyReshaper-1.1.1.dist-info/entry_points.txt
PyReshaper-1.1.1.dist-info/top_level.txt
PyReshaper-1.1.1.dist-info/RECORD
