Metadata-Version: 2.1
Name: PyReshaper
Version: 1.1.1
Summary: Python Time-Slice to Time-Series NetCDF Converter
Home-page: https://github.com/NCAR/PyReshaper
Author: Kevin Paul
Author-email: kpaul@ucar.edu
License: UNKNOWN
Platform: UNKNOWN
Classifier: Programming Language :: Python :: 3.6
Classifier: Programming Language :: Python :: 3.7
Classifier: Programming Language :: Python :: 3.8
Classifier: License :: OSI Approved :: Apache Software License
Classifier: Operating System :: OS Independent
Classifier: Topic :: Scientific/Engineering
Classifier: Topic :: Scientific/Engineering :: Atmospheric Science
Classifier: Topic :: Utilities
Requires-Python: >=3.6
Requires-Dist: asaptools
